gguf_connector/__init__.py
gguf_connector/a.py
gguf_connector/b.py
gguf_connector/b1.py
gguf_connector/b2.py
gguf_connector/b4.py
gguf_connector/c.py
gguf_connector/c1.py
gguf_connector/c2.py
gguf_connector/c3.py
gguf_connector/cg.py
gguf_connector/const.py
gguf_connector/cp.py
gguf_connector/cpp.py
gguf_connector/cs.py
gguf_connector/cu.py
gguf_connector/d.py
gguf_connector/d2.py
gguf_connector/d4.py
gguf_connector/d5.py
gguf_connector/d6.py
gguf_connector/d7.py
gguf_connector/d8.py
gguf_connector/d9.py
gguf_connector/data.json
gguf_connector/e.py
gguf_connector/e2.py
gguf_connector/e3.py
gguf_connector/e4.py
gguf_connector/e5.py
gguf_connector/e6.py
gguf_connector/e7.py
gguf_connector/e8.py
gguf_connector/e9.py
gguf_connector/ex1.py
gguf_connector/extractor.py
gguf_connector/f.py
gguf_connector/f2.py
gguf_connector/f4.py
gguf_connector/f5.py
gguf_connector/f6.py
gguf_connector/f7.py
gguf_connector/f9.py
gguf_connector/g.py
gguf_connector/g1.py
gguf_connector/g2.py
gguf_connector/g3.py
gguf_connector/gpp.py
gguf_connector/h2.py
gguf_connector/h3.py
gguf_connector/h6.py
gguf_connector/i.py
gguf_connector/i2.py
gguf_connector/k.py
gguf_connector/k0.py
gguf_connector/k1.py
gguf_connector/k2.py
gguf_connector/k3.py
gguf_connector/k4.py
gguf_connector/k5.py
gguf_connector/k6.py
gguf_connector/k7.py
gguf_connector/k8.py
gguf_connector/k9.py
gguf_connector/l.py
gguf_connector/l2.py
gguf_connector/lazy.py
gguf_connector/logo.png
gguf_connector/m.py
gguf_connector/m1.py
gguf_connector/m2.py
gguf_connector/ma.py
gguf_connector/menu.py
gguf_connector/mmj.py
gguf_connector/mt.py
gguf_connector/n.py
gguf_connector/n2.py
gguf_connector/n3.py
gguf_connector/o.py
gguf_connector/o2.py
gguf_connector/p.py
gguf_connector/p0.py
gguf_connector/p1.py
gguf_connector/p2.py
gguf_connector/p4.py
gguf_connector/p5.py
gguf_connector/p6.py
gguf_connector/p9.py
gguf_connector/pf.py
gguf_connector/pg.py
gguf_connector/pp.py
gguf_connector/ps.py
gguf_connector/q.py
gguf_connector/q0.py
gguf_connector-3.2.9.dist-info/entry_points.txt
gguf_connector-3.2.9.dist-info/LICENSE
gguf_connector-3.2.9.dist-info/WHEEL
gguf_connector-3.2.9.dist-info/METADATA
gguf_connector-3.2.9.dist-info/RECORD
