Metadata-Version: 2.1
Name: gguf-connector
Version: 3.2.9
Summary: GGUF connector(s) with GUI
Author-email: calcuis <info@calcu.io>
Classifier: License :: OSI Approved :: MIT License
Project-URL: Changelog, https://github.com/calcuis/gguf-connector/releases
Project-URL: Community, https://www.reddit.com/r/gguf
Project-URL: Download, https://github.com/calcuis/chatgpt-model-selector/releases
Project-URL: Homepage, https://gguf.us
Project-URL: Issues, https://github.com/calcuis/gguf-connector/issues
Project-URL: Repository, https://github.com/calcuis/gguf-connector
